LICENSE.rst
README.md
setup.cfg
setup.py
kdtree/__init__.py
kdtree/kdtree.py
kdtree/point.py
ranged_kdtree.egg-info/PKG-INFO
ranged_kdtree.egg-info/SOURCES.txt
ranged_kdtree.egg-info/dependency_links.txt
ranged_kdtree.egg-info/top_level.txt